{
  "search": [
    {
      "id":1
    },
    {
      "id":2
    }  
  ],
  "products":[
    {
      "id": 1,
      "productName": "HAND WASH",
      "imageUrl":"assets/icon-handwash.svg"
    },
    {
      "id": 2,
      "productName": "GLOVES",
      "imageUrl":"assets/icon-gloves.svg"
    },
    {
      "id": 3,
      "productName": "MASKS",
      "imageUrl":"assets/icon-mask.svg"
    },
    {
      "id": 4,
      "productName": "TOILET PAPER",
      "imageUrl":"assets/icon-tp.svg"
    },
    {
      "id": 5,
      "productName": "BOTTLED WATER",
      "imageUrl":"assets/icon-water.svg"
    },
    {
      "id": 6,
      "productName": "SANITARY PAD",
      "imageUrl":"assets/icon-sp.svg"
    }
  ],
  "hammer": {
    "resultCount": 8,
    "startIndex": 0,
    "items": [
      {
        "itemId": "302346658",
        "reducedTagId": null,
        "internetSku": null,
        "classification": {
          "departmentId": 0,
          "classId": 1,
          "subclassId": 2
        },
        "upc": "6940989321618",
        "productName": "16 oz. Fiberglass Claw Hammer",
        "productType": "MERCHANDISE",
        "productCode": null,
        "taxwareCode": null,
        "modelNumber": "N-G16CAV",
        "brandName": "ANViL",
        "retailPrice": 5.97,
        "retailPricingInfo": {
          "originalRetailPrice": null,
          "retailPrice": null,
          "discountedDollarOff": null,
          "priceSource": null,
          "hasBuyerMarkedDown": false
        },
        "skuNumber": "345339",
        "unitOfMeasure": "EA",
        "images": [
          "Primary|https://images.homedepot-static.com/productImages/e8d824e4-272c-4da3-8e86-ac4cd2a80ff0/svn/anvil-claw-hammers-n-g16cav-64_400.jpg"
        ],
        "description": null,
        "specifications": null,
        "dimensions": null,
        "warranty": null,
        "shippingDetails": null,
        "inStoreLocation": null,
        "quantityAvailable": 0.0,
        "vendorAvailableQuantity": 0.0,
        "active": false,
        "allowDecimals": false,
        "itemDataSource": "Catalog Api",
        "unitOfMeasureCode": 80,
        "unitOfMeasureDescription": "EACH",
        "unitCost": null,
        "vendorNumber": null,
        "vendorName": null,
        "specialOrderSku": null,
        "availabilityType": "Browse Only",
        "thdOmsSku": null,
        "shipToStoreEligible": false,
        "shipToHomeEligible": false,
        "shipToStoreStartDate": null,
        "shipToStoreEndDate": null,
        "estimatedShippingStartDate": null,
        "estimatedShippingEndDate": null,
        "quantityLimit": 0,
        "priceAdjustments": null,
        "isSpecialBuy": false,
        "swatches": null,
        "detailType": null,
        "skuFeePercent": null,
        "priceType": null,
        "eligibleToSell": true,
        "notEligibleToSellReason": null,
        "bulkRetailPrice": null,
        "sellingChannels": null,
        "allowedFulfillments": null,
        "prices": null,
        "identifiers": null,
        "mvendorChannel": null,
        "gtin": null,
        "gln": null,
        "superSku": null,
        "superSkus": null,
        "returnWindow": null,
        "backOrderable": false
      }
    ]
  },
  "dataList": [
    {
      "itemSku": "",
      "name": "Lowe's",
      "price": 62.89,
      "priceChange": 0,
      "itemDescription": "",
      "itemImageUrl": "",
      "lastUpdateTime": ""
    },
    {
      "itemSku": "",
      "name": "Ace",
      "price": 70.64,
      "priceChange": 0,
      "itemDescription": "",
      "itemImageUrl": "",
      "lastUpdateTime": ""
    },
    {
      "itemSku": "",
      "name": "Smith Hardware",
      "price": 78.48,
      "priceChange": 0,
      "itemDescription": "",
      "itemImageUrl": "",
      "lastUpdateTime": ""
    }
  ]
}
